{
  "slug": "collections/context-menu",
  "title": "ContextMenu",
  "package": {
    "name": "@choice-ui/context-menu",
    "version": "0.0.7",
    "description": "Context Menu component for Choiceform Design System",
    "dependencies": {
      "@floating-ui/react": "0.27.15",
      "usehooks-ts": "^3.1.0",
      "@choice-ui/menus": "workspace:*"
    },
    "peerDependencies": {
      "react": ">=18.0.0",
      "react-dom": ">=18.0.0"
    }
  },
  "exports": [
    "ContextMenu",
    "type ContextMenuProps"
  ],
  "props": [
    {
      "displayName": "ContextMenuProps",
      "description": "",
      "props": [
        {
          "name": "disabled",
          "type": "boolean | undefined",
          "required": false,
          "description": ""
        },
        {
          "name": "disabledNested",
          "type": "boolean | undefined",
          "required": false,
          "description": ""
        },
        {
          "name": "focusManagerProps",
          "type": "FloatingFocusManagerProps | undefined",
          "required": false,
          "description": ""
        },
        {
          "name": "offset",
          "type": "number | undefined",
          "required": false,
          "description": ""
        },
        {
          "name": "onOpenChange",
          "type": "((open: boolean) => void) | undefined",
          "required": false,
          "description": ""
        },
        {
          "name": "open",
          "type": "boolean | undefined",
          "required": false,
          "description": ""
        },
        {
          "name": "placement",
          "type": "undefined | \"top\" | \"right\" | \"bottom\" | \"left\" | \"top-start\" | \"top-end\" | \"right-start\" | \"right-end\" | \"bottom-start\" | \"bottom-end\" | \"left-start\" | \"left-end\"",
          "required": false,
          "description": ""
        },
        {
          "name": "portalId",
          "type": "string | undefined",
          "required": false,
          "description": ""
        },
        {
          "name": "readOnly",
          "type": "boolean | undefined",
          "required": false,
          "description": ""
        },
        {
          "name": "root",
          "type": "HTMLElement | null | undefined",
          "required": false,
          "description": ""
        },
        {
          "name": "selection",
          "type": "boolean | undefined",
          "required": false,
          "description": ""
        },
        {
          "name": "triggerRef",
          "type": "RefObject<HTMLElement> | undefined",
          "required": false,
          "description": ""
        },
        {
          "name": "triggerSelector",
          "type": "string | undefined",
          "required": false,
          "description": ""
        },
        {
          "name": "variant",
          "type": "undefined | \"default\" | \"light\" | \"reset\"",
          "required": false,
          "description": ""
        }
      ]
    }
  ],
  "stories": [
    {
      "id": "collections-contextmenu--basic",
      "name": "Basic",
      "exportName": "Basic",
      "description": "Basic: The simplest usage of ContextMenu.\n\nFeatures:\n- Right-click triggered context menu\n- Virtual positioning at mouse cursor location\n- Keyboard navigation support\n- Automatic dismissal on click outside\n\nImplementation notes:\n- Uses floating-ui/react for positioning and interactions\n- Fully reuses Dropdown sub-components (Content, Item, etc.)\n- Supports all standard menu features like dividers and variants",
      "source": "import { ContextMenu } from \"@choice-ui/context-menu\"\n\nexport default function App() {\n\n  return (\n    <ContextMenu>\n      <ContextMenu.Trigger>\n        <div className=\"bg-secondary-background select-none rounded-xl border border-dashed p-8\">\n          Right click me to open context menu\n        </div>\n      </ContextMenu.Trigger>\n      <ContextMenu.Content>\n        <ContextMenu.Item>\n          <ContextMenu.Value>Copy</ContextMenu.Value>\n        </ContextMenu.Item>\n        <ContextMenu.Item>\n          <ContextMenu.Value>Cut</ContextMenu.Value>\n        </ContextMenu.Item>\n        <ContextMenu.Item>\n          <ContextMenu.Value>Paste</ContextMenu.Value>\n        </ContextMenu.Item>\n        <ContextMenu.Divider />\n        <ContextMenu.Item>\n          <ContextMenu.Value>Delete</ContextMenu.Value>\n        </ContextMenu.Item>\n      </ContextMenu.Content>\n    </ContextMenu>\n  )\n\n}"
    },
    {
      "id": "collections-contextmenu--with-selection",
      "name": "With Selection",
      "exportName": "WithSelection",
      "description": "WithSelection: Demonstrates selection functionality with visual indicators.\n\nFeatures:\n- Visual selection indicator (check mark)\n- Controlled selection state\n- Selection persists between menu opens\n- Automatic menu closure on selection\n\nUsage:\n- Set `selection={true}` on the ContextMenu\n- Use `selected` prop on items to indicate selection state\n- Handle selection via `onMouseUp` callback",
      "source": "import { ContextMenu } from \"@choice-ui/context-menu\"\nimport { useState } from \"react\"\n\nexport default function App() {\n\n  const [selected, setSelected] = useState<string | null>(\"option1\")\n\n  const options = [\n    { id: \"option1\", label: \"Option 1\" },\n    { id: \"option2\", label: \"Option 2\" },\n    { id: \"option3\", label: \"Option 3\" },\n  ]\n\n  return (\n    <ContextMenu selection={true}>\n      <ContextMenu.Trigger>\n        <div className=\"bg-secondary-background select-none rounded-xl border border-dashed p-8\">\n          Right click me for selection menu\n        </div>\n      </ContextMenu.Trigger>\n      <ContextMenu.Content>\n        <ContextMenu.Label>Select an option</ContextMenu.Label>\n        {options.map((option) => (\n          <ContextMenu.Item\n            key={option.id}\n            selected={selected === option.id}\n            onMouseUp={() => setSelected(option.id)}\n          >\n            <ContextMenu.Value>{option.label}</ContextMenu.Value>\n          </ContextMenu.Item>\n        ))}\n      </ContextMenu.Content>\n    </ContextMenu>\n  )\n\n}"
    },
    {
      "id": "collections-contextmenu--with-disabled-items",
      "name": "With Disabled Items",
      "exportName": "WithDisabledItems",
      "description": "WithDisabledItems: Demonstrates disabled menu items.\n\nFeatures:\n- Visual disabled state\n- Prevents interaction with disabled items\n- Maintains keyboard navigation flow\n- Useful for conditional menu states",
      "source": "import { ContextMenu } from \"@choice-ui/context-menu\"\n\nexport default function App() {\n\n  return (\n    <ContextMenu>\n      <ContextMenu.Trigger>\n        <div className=\"bg-secondary-background rounded-xl border border-dashed p-8\">\n          Right click for menu with disabled items\n        </div>\n      </ContextMenu.Trigger>\n      <ContextMenu.Content>\n        <ContextMenu.Item>\n          <ContextMenu.Value>Available Action</ContextMenu.Value>\n        </ContextMenu.Item>\n        <ContextMenu.Item disabled>\n          <ContextMenu.Value>Disabled Action</ContextMenu.Value>\n        </ContextMenu.Item>\n        <ContextMenu.Item>\n          <ContextMenu.Value>Another Available Action</ContextMenu.Value>\n        </ContextMenu.Item>\n        <ContextMenu.Divider />\n        <ContextMenu.Item disabled>\n          <ContextMenu.Value>Also Disabled</ContextMenu.Value>\n        </ContextMenu.Item>\n      </ContextMenu.Content>\n    </ContextMenu>\n  )\n\n}"
    },
    {
      "id": "collections-contextmenu--shared-menu-content",
      "name": "Shared Menu Content",
      "exportName": "SharedMenuContent",
      "description": "SharedMenuContent: Demonstrates how to share menu content between Dropdown and ContextMenu.\n\nThis is the key business value of ContextMenu - complete component reuse.\n\nFeatures:\n- Same menu content works in both Dropdown and ContextMenu\n- Uses Dropdown components (Content, Item, etc.) for compatibility\n- Reduces code duplication and ensures consistency\n- Demonstrates the \"write once, use everywhere\" approach\n\nTechnical implementation:\n- ContextMenu internally reuses all Dropdown sub-components\n- Content is defined as JSX variable (not function component) for better compatibility\n- Both components share the same interaction patterns",
      "source": "import { ContextMenu } from \"@choice-ui/context-menu\"\n\nexport default function App() {\n\n  // Shared menu content - uses Dropdown components for compatibility\n  const sharedMenuContent = (\n    <Dropdown.Content>\n      <Dropdown.Item>\n        <Dropdown.Value>New File</Dropdown.Value>\n      </Dropdown.Item>\n      <Dropdown.Item>\n        <Dropdown.Value>New Folder</Dropdown.Value>\n      </Dropdown.Item>\n      <Dropdown.Divider />\n      <Dropdown.Item>\n        <Dropdown.Value>Import</Dropdown.Value>\n      </Dropdown.Item>\n      <Dropdown.Item>\n        <Dropdown.Value>Export</Dropdown.Value>\n      </Dropdown.Item>\n    </Dropdown.Content>\n  )\n\n  return (\n    <div className=\"flex flex-col gap-8\">\n      {/* Dropdown using shared menu content */}\n      <div>\n        <p className=\"mb-2\">Dropdown with shared menu content</p>\n\n        <Dropdown>\n          <Dropdown.Trigger>\n            <Dropdown.Value>Click for Dropdown Menu</Dropdown.Value>\n          </Dropdown.Trigger>\n          {sharedMenuContent}\n        </Dropdown>\n      </div>\n\n      {/* ContextMenu using the same content */}\n      <div>\n        <p className=\"mb-2\">Context menu with same content</p>\n        <ContextMenu>\n          <ContextMenu.Trigger>\n            <div className=\"bg-secondary-background rounded-xl border border-dashed p-8\">\n              Right click me for context menu (same content)\n            </div>\n          </ContextMenu.Trigger>\n          {sharedMenuContent}\n        </ContextMenu>\n      </div>\n    </div>\n  )\n\n}"
    },
    {
      "id": "collections-contextmenu--with-dividers",
      "name": "With Dividers",
      "exportName": "WithDividers",
      "description": "WithDividers: Shows complex menu structure with dividers and labels.\n\nFeatures:\n- Section labels for grouping\n- Visual dividers for separation\n- Different item variants (danger, highlight)\n- Hierarchical menu organization\n\nUse cases:\n- File manager context menus\n- Complex application menus\n- Settings and configuration menus",
      "source": "import { ContextMenu } from \"@choice-ui/context-menu\"\n\nexport default function App() {\n\n  return (\n    <ContextMenu>\n      <ContextMenu.Trigger>\n        <div className=\"bg-secondary-background rounded-xl border border-dashed p-8 text-center\">\n          Right click for complex menu\n        </div>\n      </ContextMenu.Trigger>\n      <ContextMenu.Content>\n        <ContextMenu.Label>File Operations</ContextMenu.Label>\n        <ContextMenu.Item>\n          <ContextMenu.Value>Open</ContextMenu.Value>\n        </ContextMenu.Item>\n        <ContextMenu.Item>\n          <ContextMenu.Value>Open in New Tab</ContextMenu.Value>\n        </ContextMenu.Item>\n        <ContextMenu.Divider />\n        <ContextMenu.Label>Edit Operations</ContextMenu.Label>\n        <ContextMenu.Item>\n          <ContextMenu.Value>Cut</ContextMenu.Value>\n        </ContextMenu.Item>\n        <ContextMenu.Item>\n          <ContextMenu.Value>Copy</ContextMenu.Value>\n        </ContextMenu.Item>\n        <ContextMenu.Item>\n          <ContextMenu.Value>Paste</ContextMenu.Value>\n        </ContextMenu.Item>\n        <ContextMenu.Divider />\n        <ContextMenu.Item variant=\"danger\">\n          <ContextMenu.Value>Delete</ContextMenu.Value>\n        </ContextMenu.Item>\n      </ContextMenu.Content>\n    </ContextMenu>\n  )\n\n}"
    },
    {
      "id": "collections-contextmenu--nested-submenus",
      "name": "Nested Submenus",
      "exportName": "NestedSubmenus",
      "description": "NestedSubmenus: Demonstrates nested context menus with multiple levels.\n\nFeatures:\n- Multiple levels of nested submenus\n- Hover-based submenu activation (hover over submenu triggers)\n- Keyboard navigation across nested levels (use arrow keys)\n- Automatic submenu positioning (prevents overflow)\n- Mixed content (regular items + submenus)\n\nImplementation:\n- Uses nested ContextMenu components for submenus\n- SubTrigger components indicate expandable items (show arrow icon)\n- Supports unlimited nesting depth\n- Maintains consistent interaction patterns\n\nUse cases:\n- File explorer context menus\n- Complex application menus\n- Hierarchical command structures\n- Multi-level category selections",
      "source": "import { ContextMenu } from \"@choice-ui/context-menu\"\n\nexport default function App() {\n\n  return (\n    <ContextMenu>\n      <ContextMenu.Trigger>\n        <div className=\"bg-secondary-background rounded-xl border border-dashed p-8 text-center\">\n          Right click for nested menus\n        </div>\n      </ContextMenu.Trigger>\n      <ContextMenu.Content>\n        <ContextMenu.Item>\n          <ContextMenu.Value>Cut</ContextMenu.Value>\n        </ContextMenu.Item>\n        <ContextMenu.Item>\n          <ContextMenu.Value>Copy</ContextMenu.Value>\n        </ContextMenu.Item>\n        <ContextMenu.Item>\n          <ContextMenu.Value>Paste</ContextMenu.Value>\n        </ContextMenu.Item>\n        <ContextMenu.Divider />\n\n        {/* First level submenu - Share (no Target needed for nested) */}\n        <ContextMenu>\n          <ContextMenu.SubTrigger>\n            <ContextMenu.Value>Share</ContextMenu.Value>\n          </ContextMenu.SubTrigger>\n          <ContextMenu.Content>\n            <ContextMenu.Item>\n              <ContextMenu.Value>Copy Link</ContextMenu.Value>\n            </ContextMenu.Item>\n            <ContextMenu.Item>\n              <ContextMenu.Value>Email</ContextMenu.Value>\n            </ContextMenu.Item>\n\n            {/* Second level submenu - Social Media (also no Target) */}\n            <ContextMenu>\n              <ContextMenu.SubTrigger>\n                <ContextMenu.Value>Social Media</ContextMenu.Value>\n              </ContextMenu.SubTrigger>\n              <ContextMenu.Content>\n                <ContextMenu.Item>\n                  <ContextMenu.Value>Twitter</ContextMenu.Value>\n                </ContextMenu.Item>\n                <ContextMenu.Item>\n                  <ContextMenu.Value>Facebook</ContextMenu.Value>\n                </ContextMenu.Item>\n                <ContextMenu.Item>\n                  <ContextMenu.Value>LinkedIn</ContextMenu.Value>\n                </ContextMenu.Item>\n              </ContextMenu.Content>\n            </ContextMenu>\n\n            <ContextMenu.Divider />\n            <ContextMenu.Item>\n              <ContextMenu.Value>Generate QR Code</ContextMenu.Value>\n            </ContextMenu.Item>\n          </ContextMenu.Content>\n        </ContextMenu>\n\n        {/* First level submenu - Export */}\n        <ContextMenu>\n          <ContextMenu.SubTrigger>\n            <ContextMenu.Value>Export</ContextMenu.Value>\n          </ContextMenu.SubTrigger>\n          <ContextMenu.Content>\n            <ContextMenu.Label>File Formats</ContextMenu.Label>\n            <ContextMenu.Item>\n              <ContextMenu.Value>PDF</ContextMenu.Value>\n            </ContextMenu.Item>\n            <ContextMenu.Item>\n              <ContextMenu.Value>PNG</ContextMenu.Value>\n            </ContextMenu.Item>\n            <ContextMenu.Item>\n              <ContextMenu.Value>SVG</ContextMenu.Value>\n            </ContextMenu.Item>\n            <ContextMenu.Divider />\n\n            {/* Second level submenu - Advanced Options */}\n            <ContextMenu>\n              <ContextMenu.SubTrigger>\n                <ContextMenu.Value>Advanced Options</ContextMenu.Value>\n              </ContextMenu.SubTrigger>\n              <ContextMenu.Content>\n                <ContextMenu.Item>\n                  <ContextMenu.Value>High Quality</ContextMenu.Value>\n                </ContextMenu.Item>\n                <ContextMenu.Item>\n                  <ContextMenu.Value>Compressed</ContextMenu.Value>\n                </ContextMenu.Item>\n                <ContextMenu.Divider />\n                <ContextMenu.Item>\n                  <ContextMenu.Value>Custom Settings</ContextMenu.Value>\n                </ContextMenu.Item>\n              </ContextMenu.Content>\n            </ContextMenu>\n          </ContextMenu.Content>\n        </ContextMenu>\n\n        <ContextMenu.Divider />\n        <ContextMenu.Item>\n          <ContextMenu.Value>Properties</ContextMenu.Value>\n        </ContextMenu.Item>\n        <ContextMenu.Item variant=\"danger\">\n          <ContextMenu.Value>Delete</ContextMenu.Value>\n        </ContextMenu.Item>\n      </ContextMenu.Content>\n    </ContextMenu>\n  )\n\n}"
    },
    {
      "id": "collections-contextmenu--context-menu-nested-dropdown",
      "name": "Context Menu Nested Dropdown",
      "exportName": "ContextMenuNestedDropdown",
      "description": "ContextMenuNestedDropdown: Fixed implementation using triggerRef to avoid component conflicts.\n\nThis story demonstrates the solution to the original nesting problem:\n- ContextMenu.Target was interfering with Dropdown's Slot mechanism\n- Using triggerRef bypasses the wrapper issue entirely\n- Both components now work perfectly together\n\nFeatures:\n- Left-click opens Dropdown menu\n- Right-click opens ContextMenu\n- No component wrapping conflicts\n- Clean, working implementation",
      "source": "import { ContextMenu } from \"@choice-ui/context-menu\"\nimport { useRef } from \"react\"\n\nexport default function App() {\n\n  const triggerRef = useRef<HTMLDivElement>(null)\n\n  const ContextMenuContent = () => (\n    <>\n      <ContextMenu.Item>\n        <ContextMenu.Value>Available Action</ContextMenu.Value>\n      </ContextMenu.Item>\n      <ContextMenu.Item>\n        <ContextMenu.Value>Another Available Action</ContextMenu.Value>\n      </ContextMenu.Item>\n      <ContextMenu.Divider />\n      <ContextMenu.Item>\n        <ContextMenu.Value>Another Available Action</ContextMenu.Value>\n      </ContextMenu.Item>\n      <ContextMenu.Divider />\n      <ContextMenu.Item>\n        <ContextMenu.Value>Another Available Action</ContextMenu.Value>\n      </ContextMenu.Item>\n    </>\n  )\n\n  return (\n    <div className=\"flex items-center justify-center\">\n      <div\n        ref={triggerRef}\n        className=\"bg-secondary-background rounded-xl border border-dashed p-8\"\n      >\n        <Dropdown>\n          <Dropdown.Trigger>\n            <Dropdown.Value>Left/Right click for different menus</Dropdown.Value>\n          </Dropdown.Trigger>\n          <Dropdown.Content>\n            <ContextMenuContent />\n          </Dropdown.Content>\n        </Dropdown>\n      </div>\n\n      <ContextMenu triggerRef={triggerRef}>\n        <ContextMenu.Content>\n          <ContextMenuContent />\n        </ContextMenu.Content>\n      </ContextMenu>\n    </div>\n  )\n\n}"
    },
    {
      "id": "collections-contextmenu--nested-submenu-with-long-list",
      "name": "Nested Submenu With Long List",
      "exportName": "NestedSubmenuWithLongList",
      "description": "NestedSubmenuWithLongList: Tests scrolling functionality in nested submenus.\n\nThis story specifically tests the fix for nested menu scrolling:\n- First level menu with many items\n- Nested submenu with a long list that exceeds screen height\n- Verifies scroll arrows appear correctly\n- Verifies scrolling works properly in nested menus\n- Tests height constraints are properly applied\n\nExpected behavior:\n- Nested submenu should show scroll arrows when content exceeds available height\n- Users should be able to scroll through all items in the nested menu\n- Menu should not overflow beyond screen boundaries\n- Scroll arrows should appear/disappear based on scroll position\n\nThis story validates the fix for nested menu scrolling issues.",
      "source": "import { ContextMenu } from \"@choice-ui/context-menu\"\n\nexport default function App() {\n\n  // Generate a long list of items for testing scrolling\n  const longListItems = Array.from({ length: 30 }, (_, i) => ({\n    id: `item-${i + 1}`,\n    label: `Menu Item ${i + 1}`,\n  }))\n\n  return (\n    <ContextMenu>\n      <ContextMenu.Trigger>\n        <div className=\"bg-secondary-background rounded-xl border border-dashed p-8 text-center\">\n          Right click for menu with long nested submenu\n          <br />\n          <span className=\"text-body-small text-gray-500\">\n            Hover over &quot;Long List&quot; to see scrolling submenu\n          </span>\n        </div>\n      </ContextMenu.Trigger>\n      <ContextMenu.Content>\n        <ContextMenu.Item>\n          <ContextMenu.Value>Cut</ContextMenu.Value>\n        </ContextMenu.Item>\n        <ContextMenu.Item>\n          <ContextMenu.Value>Copy</ContextMenu.Value>\n        </ContextMenu.Item>\n        <ContextMenu.Item>\n          <ContextMenu.Value>Paste</ContextMenu.Value>\n        </ContextMenu.Item>\n        <ContextMenu.Divider />\n\n        {/* Nested submenu with long list - this should scroll */}\n        <ContextMenu>\n          <ContextMenu.SubTrigger>\n            <ContextMenu.Value>Long List</ContextMenu.Value>\n          </ContextMenu.SubTrigger>\n          <ContextMenu.Content>\n            <ContextMenu.Label>Scrollable Items</ContextMenu.Label>\n            {longListItems.map((item) => (\n              <ContextMenu.Item key={item.id}>\n                <ContextMenu.Value>{item.label}</ContextMenu.Value>\n              </ContextMenu.Item>\n            ))}\n          </ContextMenu.Content>\n        </ContextMenu>\n\n        {/* Another nested submenu with long list for comparison */}\n        <ContextMenu>\n          <ContextMenu.SubTrigger>\n            <ContextMenu.Value>Another Long List</ContextMenu.Value>\n          </ContextMenu.SubTrigger>\n          <ContextMenu.Content>\n            <ContextMenu.Label>Another Scrollable List</ContextMenu.Label>\n            {longListItems.slice(0, 25).map((item) => (\n              <ContextMenu.Item key={item.id}>\n                <ContextMenu.Value>{item.label}</ContextMenu.Value>\n              </ContextMenu.Item>\n            ))}\n          </ContextMenu.Content>\n        </ContextMenu>\n\n        <ContextMenu.Divider />\n        <ContextMenu.Item>\n          <ContextMenu.Value>Properties</ContextMenu.Value>\n        </ContextMenu.Item>\n        <ContextMenu.Item variant=\"danger\">\n          <ContextMenu.Value>Delete</ContextMenu.Value>\n        </ContextMenu.Item>\n      </ContextMenu.Content>\n    </ContextMenu>\n  )\n\n}"
    },
    {
      "id": "collections-contextmenu--with-trigger-ref",
      "name": "With Trigger Ref",
      "exportName": "WithTriggerRef",
      "description": "WithTriggerRef: Demonstrates using triggerRef to avoid component wrapping conflicts.\n\nThis approach solves complex nesting scenarios by:\n- Using a ref to directly bind the context menu to any DOM element\n- Avoiding wrapper components that might interfere with other libraries\n- Providing maximum flexibility for integration\n\nFeatures:\n- Left-click opens Dropdown normally\n- Right-click opens ContextMenu via triggerRef\n- No component wrapping conflicts\n- Clean separation of concerns",
      "source": "import { ContextMenu } from \"@choice-ui/context-menu\"\nimport { useRef } from \"react\"\n\nexport default function App() {\n\n  const triggerRef = useRef<HTMLDivElement>(null)\n\n  const MenuContent = () => (\n    <>\n      <ContextMenu.Item>\n        <ContextMenu.Value>Copy</ContextMenu.Value>\n      </ContextMenu.Item>\n      <ContextMenu.Item>\n        <ContextMenu.Value>Cut</ContextMenu.Value>\n      </ContextMenu.Item>\n      <ContextMenu.Item>\n        <ContextMenu.Value>Paste</ContextMenu.Value>\n      </ContextMenu.Item>\n      <ContextMenu.Divider />\n      <ContextMenu.Item variant=\"danger\">\n        <ContextMenu.Value>Delete</ContextMenu.Value>\n      </ContextMenu.Item>\n    </>\n  )\n\n  return (\n    <div className=\"flex items-center justify-center\">\n      <div\n        ref={triggerRef}\n        className=\"bg-secondary-background rounded-xl border border-dashed p-8\"\n      >\n        <Dropdown>\n          <Dropdown.Trigger>\n            <Dropdown.Value>Left click for Dropdown, Right click for ContextMenu</Dropdown.Value>\n          </Dropdown.Trigger>\n          <Dropdown.Content>\n            <Dropdown.Label>Dropdown Menu</Dropdown.Label>\n            <Dropdown.Item>\n              <Dropdown.Value>New File</Dropdown.Value>\n            </Dropdown.Item>\n            <Dropdown.Item>\n              <Dropdown.Value>New Folder</Dropdown.Value>\n            </Dropdown.Item>\n            <Dropdown.Divider />\n            <Dropdown.Item>\n              <Dropdown.Value>Settings</Dropdown.Value>\n            </Dropdown.Item>\n          </Dropdown.Content>\n        </Dropdown>\n      </div>\n\n      <ContextMenu triggerRef={triggerRef}>\n        <ContextMenu.Content>\n          <ContextMenu.Label>Context Menu</ContextMenu.Label>\n          <MenuContent />\n        </ContextMenu.Content>\n      </ContextMenu>\n    </div>\n  )\n\n}"
    },
    {
      "id": "collections-contextmenu--with-trigger-selector",
      "name": "With Trigger Selector",
      "exportName": "WithTriggerSelector",
      "description": "WithTriggerSelector: Demonstrates using triggerSelector (CSS selector) instead of triggerRef.\n\nThis approach is useful when:\n- You cannot access the element via ref (e.g., third-party components)\n- The trigger element is rendered elsewhere in the DOM\n- You prefer a simpler, selector-based approach\n\nFeatures:\n- Supports any valid CSS selector (#id, .class, [data-*], etc.)\n- Same functionality as triggerRef\n- triggerRef takes priority if both are provided",
      "source": "import { ContextMenu } from \"@choice-ui/context-menu\"\n\nexport default function App() {\n\n  return (\n    <div className=\"flex gap-8\">\n      {/* Using id selector */}\n      <div>\n        <p className=\"text-body-small-strong mb-2\">Using #id selector</p>\n        <div\n          id=\"context-menu-trigger-by-id\"\n          className=\"bg-secondary-background rounded-lg border border-dashed p-8\"\n        >\n          Right click me (id selector)\n        </div>\n        <ContextMenu triggerSelector=\"#context-menu-trigger-by-id\">\n          <ContextMenu.Content>\n            <ContextMenu.Label>ID Selector Menu</ContextMenu.Label>\n            <ContextMenu.Item>\n              <ContextMenu.Value>Action 1</ContextMenu.Value>\n            </ContextMenu.Item>\n            <ContextMenu.Item>\n              <ContextMenu.Value>Action 2</ContextMenu.Value>\n            </ContextMenu.Item>\n          </ContextMenu.Content>\n        </ContextMenu>\n      </div>\n\n      {/* Using class selector */}\n      <div>\n        <p className=\"text-body-small-strong mb-2\">Using .class selector</p>\n        <div className=\"context-menu-trigger-by-class bg-secondary-background rounded-lg border border-dashed p-8\">\n          Right click me (class selector)\n        </div>\n        <ContextMenu triggerSelector=\".context-menu-trigger-by-class\">\n          <ContextMenu.Content>\n            <ContextMenu.Label>Class Selector Menu</ContextMenu.Label>\n            <ContextMenu.Item>\n              <ContextMenu.Value>Option A</ContextMenu.Value>\n            </ContextMenu.Item>\n            <ContextMenu.Item>\n              <ContextMenu.Value>Option B</ContextMenu.Value>\n            </ContextMenu.Item>\n          </ContextMenu.Content>\n        </ContextMenu>\n      </div>\n\n      {/* Using data attribute selector */}\n      <div>\n        <p className=\"text-body-small-strong mb-2\">Using [data-*] selector</p>\n        <div\n          data-context-trigger=\"custom\"\n          className=\"bg-secondary-background rounded-lg border border-dashed p-8\"\n        >\n          Right click me (data-* selector)\n        </div>\n        <ContextMenu triggerSelector=\"[data-context-trigger='custom']\">\n          <ContextMenu.Content>\n            <ContextMenu.Label>Data Attribute Menu</ContextMenu.Label>\n            <ContextMenu.Item>\n              <ContextMenu.Value>Item X</ContextMenu.Value>\n            </ContextMenu.Item>\n            <ContextMenu.Item>\n              <ContextMenu.Value>Item Y</ContextMenu.Value>\n            </ContextMenu.Item>\n          </ContextMenu.Content>\n        </ContextMenu>\n      </div>\n    </div>\n  )\n\n}"
    },
    {
      "id": "collections-contextmenu--with-disabled",
      "name": "With Disabled",
      "exportName": "WithDisabled",
      "description": "WithDisabled: Demonstrates disabled ContextMenu functionality.\n\nFeatures:\n- Shows how to disable the entire context menu\n- Right-click events are prevented when disabled=true\n- Visual feedback through data attributes for styling\n- Useful for conditional menu availability\n\nImplementation:\n- Set disabled={true} to prevent context menu activation\n- Can use CSS selectors like [data-disabled] for styling\n- Both Target and triggerRef approaches support disabled state",
      "source": "import { ContextMenu } from \"@choice-ui/context-menu\"\nimport { useState } from \"react\"\n\nexport default function App() {\n\n  const [isDisabled, setIsDisabled] = useState(false)\n\n  return (\n    <div className=\"space-y-8 p-8\">\n      <Checkbox\n        value={isDisabled}\n        onChange={setIsDisabled}\n      >\n        Disable context menu\n      </Checkbox>\n\n      <div className=\"flex gap-8\">\n        {/* Using ContextMenu.Trigger */}\n        <div>\n          <p className=\"text-body-small-strong mb-2\">Using ContextMenu.Trigger</p>\n          <ContextMenu disabled={isDisabled}>\n            <ContextMenu.Trigger>\n              <div className=\"bg-secondary-background rounded-xl border border-dashed p-8\">\n                {isDisabled ? \"Context menu disabled\" : \"Right click me\"}\n              </div>\n            </ContextMenu.Trigger>\n            <ContextMenu.Content>\n              <ContextMenu.Item>\n                <ContextMenu.Value>Copy</ContextMenu.Value>\n              </ContextMenu.Item>\n              <ContextMenu.Item>\n                <ContextMenu.Value>Cut</ContextMenu.Value>\n              </ContextMenu.Item>\n              <ContextMenu.Item>\n                <ContextMenu.Value>Paste</ContextMenu.Value>\n              </ContextMenu.Item>\n              <ContextMenu.Divider />\n              <ContextMenu.Item variant=\"danger\">\n                <ContextMenu.Value>Delete</ContextMenu.Value>\n              </ContextMenu.Item>\n            </ContextMenu.Content>\n          </ContextMenu>\n        </div>\n\n        {/* Using triggerRef */}\n        <div>\n          <p className=\"text-body-small-strong mb-2\">Using triggerRef</p>\n          <DisabledWithTriggerRef disabled={isDisabled} />\n        </div>\n      </div>\n\n      <div className=\"bg-secondary-background rounded-xl p-4\">\n        <strong>Tip:</strong> When disabled=true, the context menu will not open on right-click.\n        You can style disabled states using CSS selectors like <code>[data-disabled]</code> or\n        <code>[data-context-menu-disabled]</code>.\n      </div>\n    </div>\n  )\n\n}"
    },
    {
      "id": "collections-contextmenu--nested-context-menu-in-popover",
      "name": "Nested Context Menu In Popover",
      "exportName": "NestedContextMenuInPopover",
      "description": "Nested context menu in popover",
      "source": "import { ContextMenu } from \"@choice-ui/context-menu\"\nimport { useRef } from \"react\"\n\nexport default function App() {\n\n  const triggerRef = useRef<HTMLDivElement>(null)\n\n  const Item = () => {\n    return (\n      <>\n        <div\n          ref={triggerRef}\n          className=\"p-8\"\n        >\n          Right click me for selection menu\n        </div>\n        <ContextMenu\n          disabledNested\n          triggerRef={triggerRef}\n        >\n          <ContextMenu.Content>\n            <ContextMenu.Item>\n              <ContextMenu.Value>Copy</ContextMenu.Value>\n            </ContextMenu.Item>\n            <ContextMenu.Item>\n              <ContextMenu.Value>Cut</ContextMenu.Value>\n            </ContextMenu.Item>\n            <ContextMenu.Item>\n              <ContextMenu.Value>Paste</ContextMenu.Value>\n            </ContextMenu.Item>\n            <ContextMenu.Divider />\n            <ContextMenu.Item variant=\"danger\">\n              <ContextMenu.Value>Delete</ContextMenu.Value>\n            </ContextMenu.Item>\n          </ContextMenu.Content>\n        </ContextMenu>\n      </>\n    )\n  }\n\n  return (\n    <>\n      <Popover>\n        <Popover.Trigger>\n          <Button>Open Popover</Button>\n        </Popover.Trigger>\n\n        <Popover.Content>\n          <Item />\n        </Popover.Content>\n      </Popover>\n    </>\n  )\n\n}"
    },
    {
      "id": "collections-contextmenu--light",
      "name": "Light",
      "exportName": "Light",
      "description": "ContextMenu component in light variant.",
      "source": "import { ContextMenu } from \"@choice-ui/context-menu\"\n\nexport default function App() {\n\n  return (\n    <ContextMenu variant=\"light\">\n      <ContextMenu.Trigger className=\"rounded-lg border p-8\">\n        <ContextMenu.Value>Right click me for context menu</ContextMenu.Value>\n      </ContextMenu.Trigger>\n      <ContextMenu.Content>\n        <ContextMenu.Item>\n          <ContextMenu.Value>Copy</ContextMenu.Value>\n        </ContextMenu.Item>\n        <ContextMenu.Item>\n          <ContextMenu.Value>Cut</ContextMenu.Value>\n        </ContextMenu.Item>\n      </ContextMenu.Content>\n      <ContextMenu.Divider />\n      <ContextMenu.Item variant=\"danger\">\n        <ContextMenu.Value>Delete</ContextMenu.Value>\n      </ContextMenu.Item>\n    </ContextMenu>\n  )\n\n}"
    }
  ],
  "tags": [
    "upgrade"
  ]
}