{
  "slug": "layouts/loader",
  "title": "Loader",
  "package": {
    "name": "@choice-ui/loader",
    "version": "0.0.1",
    "description": "Loader component for Choiceform Design System",
    "dependencies": {
      "framer-motion": "^11",
      "@choice-ui/shared": "workspace:*"
    },
    "peerDependencies": {
      "react": ">=18.0.0",
      "react-dom": ">=18.0.0"
    }
  },
  "exports": [
    "Loader",
    "loaderVariants",
    "type LoaderProps",
    "type LoaderStage",
    "useLoader"
  ],
  "props": [
    {
      "displayName": "Loader",
      "description": "",
      "props": [
        {
          "name": "currentStage",
          "type": "number | undefined",
          "required": false,
          "description": ""
        },
        {
          "name": "duration",
          "type": "number | undefined",
          "required": false,
          "description": ""
        },
        {
          "name": "onStageChange",
          "type": "((stage: number) => void) | undefined",
          "required": false,
          "description": ""
        },
        {
          "name": "stages",
          "type": "LoaderStage[]",
          "required": true,
          "description": ""
        }
      ]
    }
  ],
  "stories": [
    {
      "id": "layouts-loader--default",
      "name": "Default",
      "exportName": "Default",
      "description": "",
      "source": ""
    },
    {
      "id": "layouts-loader--with-multiple-icons",
      "name": "With Multiple Icons",
      "exportName": "WithMultipleIcons",
      "description": "",
      "source": ""
    },
    {
      "id": "layouts-loader--controlled",
      "name": "Controlled",
      "exportName": "Controlled",
      "description": "",
      "source": "import { Loader } from \"@choice-ui/loader\"\n\nexport default function App() {\n  return (\n    <div className=\"flex flex-col items-center gap-8\">\n      <Loader\n        stages={stages}\n        currentStage={stage}\n      />\n      <div className=\"flex gap-2\">\n        <Button\n          onClick={() => setStage(0)}\n          variant={stage === 0 ? \"primary\" : \"secondary\"}\n        >\n          Step 1\n        </Button>\n        <Button\n          onClick={() => setStage(1)}\n          variant={stage === 1 ? \"primary\" : \"secondary\"}\n        >\n          Step 2\n        </Button>\n        <Button\n          onClick={() => setStage(2)}\n          variant={stage === 2 ? \"primary\" : \"secondary\"}\n        >\n          Step 3\n        </Button>\n        <Button\n          onClick={() => setStage(3)}\n          variant={stage === 3 ? \"primary\" : \"secondary\"}\n        >\n          Complete\n        </Button>\n      </div>\n    </div>\n  );\n}"
    },
    {
      "id": "layouts-loader--fast-animation",
      "name": "Fast Animation",
      "exportName": "FastAnimation",
      "description": "",
      "source": ""
    },
    {
      "id": "layouts-loader--build-process",
      "name": "Build Process",
      "exportName": "BuildProcess",
      "description": "",
      "source": ""
    },
    {
      "id": "layouts-loader--file-upload",
      "name": "File Upload",
      "exportName": "FileUpload",
      "description": "",
      "source": ""
    },
    {
      "id": "layouts-loader--with-callback",
      "name": "With Callback",
      "exportName": "WithCallback",
      "description": "",
      "source": "import { Loader } from \"@choice-ui/loader\"\n\nexport default function App() {\n  return (\n    <div className=\"flex flex-col items-center gap-8\">\n      <Loader\n        stages={stages}\n        onStageChange={handleStageChange}\n      />\n      <div className=\"bg-secondary/20 mt-4 max-h-32 w-80 overflow-auto rounded-lg p-4\">\n        <div className=\"font-mono text-xs\">\n          {log.length === 0 ? (\n            <span className=\"text-muted-foreground\">Stage changes will appear here...</span>\n          ) : (\n            log.map((entry, i) => <div key={i}>{entry}</div>)\n          )}\n        </div>\n      </div>\n    </div>\n  );\n}"
    }
  ]
}