{
  "slug": "status/notifications",
  "title": "Notifications",
  "package": {
    "name": "@choice-ui/notifications",
    "version": "0.0.3",
    "description": "Notifications component for Choiceform Design System",
    "dependencies": {
      "sonner": "^2.0.7",
      "usehooks-ts": "^3.1.0",
      "@choice-ui/shared": "workspace:*"
    },
    "peerDependencies": {
      "react": ">=18.0.0",
      "react-dom": ">=18.0.0"
    }
  },
  "exports": [
    "type NotificationsProps",
    "Toast",
    "notifications"
  ],
  "props": [
    {
      "displayName": "Toast",
      "description": "",
      "props": [
        {
          "name": "className",
          "type": "string | undefined",
          "required": false,
          "description": ""
        },
        {
          "name": "actions",
          "type": "((id: string | number) => { action?: { content: ReactNode; onClick: () => void; } | undefined; dismiss?: { content: ReactNode; onClick: () => void; } | undefined; }) | undefined",
          "required": false,
          "description": ""
        },
        {
          "name": "html",
          "type": "string | undefined",
          "required": false,
          "description": ""
        },
        {
          "name": "icon",
          "type": "ReactNode",
          "required": false,
          "description": ""
        },
        {
          "name": "text",
          "type": "string | undefined",
          "required": false,
          "description": ""
        },
        {
          "name": "toasterId",
          "type": "string | undefined",
          "required": false,
          "description": ""
        }
      ]
    }
  ],
  "stories": [
    {
      "id": "status-notifications--basic",
      "name": "Basic",
      "exportName": "Basic",
      "description": "`Notifications` is a versatile toast-style notification system for displaying temporary messages and alerts.\n\nFeatures:\n- Non-intrusive toast-style notifications\n- Customizable duration and placement\n- Support for icons to enhance visual context\n- Action buttons for user interaction\n- Dismiss functionality for user control\n- Automatic dismissal after timeout\n- Built on Sonner toast library for reliability\n\nUsage Guidelines:\n- Use for non-critical feedback and updates\n- Keep messages concise and actionable\n- Include icons to provide visual context\n- Add action buttons for common responses\n- Always provide a way to dismiss notifications\n- Consider duration based on message importance\n\nAccessibility:\n- Notifications are announced to screen readers\n- Focus management for interactive notifications\n- Timeout periods consider reading time\n- Proper contrast for all notification variants\n- Keyboard accessible actions and dismiss controls\nBasic: Demonstrates the Notifications component with various configurations.\n\nFeatures:\n- Simple notification with icon and text\n- Notification with a single action button\n- Notification with both action and dismiss buttons\n- Integration with Dialog component for action follow-up\n\nThis example showcases three common notification patterns:\n1. Basic informational notification\n2. Notification with a primary action\n3. Notification with both primary and dismiss actions\n\nThe notifications appear in the bottom-right corner of the screen\nand automatically dismiss after a timeout period, or when the user\ntakes an action.",
      "source": "import { notifications } from \"@choice-ui/notifications\"\n\nexport default function App() {\n  return (\n    <div className=\"flex gap-4\">\n      <Toaster />\n\n      <Dialog\n        open={open}\n        onOpenChange={setOpen}\n      >\n        <Dialog.Header title=\"Lorem ipsum dolor sit amet\" />\n        <Dialog.Content className=\"w-96 p-4\">\n          Lorem ipsum dolor sit amet, consectetur adipiscing elit. Sed do eiusmod tempor\n          incididunt ut labore et dolore magna aliqua.\n        </Dialog.Content>\n      </Dialog>\n\n      <Button\n        variant=\"secondary\"\n        onClick={() => {\n          notifications({\n            icon: <LayoutWallpaper />,\n            text: \"Lorem ipsum dolor sit amet, consectetur adipiscing elit. Sed do eiusmod tempor incididunt ut labore et dolore magna aliqua.\",\n          })\n        }}\n      >\n        Basic Notification\n      </Button>\n\n      <Button\n        variant=\"secondary\"\n        onClick={() => {\n          notifications({\n            html: \"Lorem ipsum dolor sit amet, <strong class='text-red-500'>consectetur adipiscing elit</strong>. Sed do eiusmod tempor incididunt ut labore et dolore magna aliqua.\",\n          })\n        }}\n      >\n        HTML Notification\n      </Button>\n\n      <Button\n        variant=\"secondary\"\n        onClick={() => {\n          notifications({\n            icon: <LayoutWallpaper />,\n            text: \"Lorem ipsum dolor sit amet, consectetur adipiscing elit. Sed do eiusmod tempor incididunt ut labore et dolore magna aliqua.\",\n            actions: (id) => ({\n              action: {\n                content: \"Reply\",\n                onClick: () => {\n                  setOpen(true)\n                  sonnerToast.dismiss(id)\n                },\n              },\n            }),\n          })\n        }}\n      >\n        Notification with actions\n      </Button>\n\n      <Button\n        variant=\"secondary\"\n        onClick={() => {\n          notifications({\n            icon: <LayoutWallpaper />,\n            text: \"Lorem ipsum dolor sit amet, consectetur adipiscing elit. Sed do eiusmod tempor incididunt ut labore et dolore magna aliqua.\",\n            actions: (id) => ({\n              action: {\n                content: \"Reply\",\n                onClick: () => {\n                  setOpen(true)\n                  sonnerToast.dismiss(id)\n                },\n              },\n              dismiss: {\n                content: \"Dismiss\",\n                onClick: () => {\n                  sonnerToast.dismiss(id)\n                },\n              },\n            }),\n          })\n        }}\n      >\n        Notification with actions and dismiss\n      </Button>\n\n      <Button\n        variant=\"secondary\"\n        onClick={() => {\n          notifications({\n            icon: \"🎉\",\n            html: \"Duplicated project <b>Original Project</b> to <b>New Project Copy</b>\",\n            actions: (id) => ({\n              action: {\n                content: \"View Project\",\n                onClick: () => {\n                  setOpen(true)\n                  sonnerToast.dismiss(id)\n                },\n              },\n              dismiss: {\n                content: \"Dismiss\",\n                onClick: () => {\n                  sonnerToast.dismiss(id)\n                },\n              },\n            }),\n          })\n        }}\n      >\n        Notification with HTML content\n      </Button>\n    </div>\n  );\n}"
    },
    {
      "id": "status-notifications--multiple-toasters",
      "name": "Multiple Toasters",
      "exportName": "MultipleToasters",
      "description": "",
      "source": "import { notifications } from \"@choice-ui/notifications\"\n\nexport default function App() {\n  return (\n    <div className=\"flex flex-col gap-4\">\n      <Toaster id=\"notifications-main\" />\n      <Toaster\n        id=\"notifications-secondary\"\n        offset={{ bottom: \"128px\" }}\n      />\n      <Toaster\n        id=\"notifications-sidebar\"\n        offset={{ right: \"128px\" }}\n      />\n\n      <div className=\"flex flex-col gap-2\">\n        <h3 className=\"text-body-large-strong\">Main Toaster</h3>\n        <div className=\"flex gap-2\">\n          <Button\n            variant=\"secondary\"\n            onClick={() => {\n              notifications({\n                toasterId: \"notifications-main\",\n                icon: <LayoutWallpaper />,\n                text: \"This notification appears in the main toaster at bottom-right.\",\n              })\n            }}\n          >\n            Main Toaster\n          </Button>\n          <Button\n            variant=\"secondary\"\n            onClick={() => {\n              notifications({\n                toasterId: \"notifications-main\",\n                icon: \"✅\",\n                text: \"Success notification in main toaster\",\n                actions: (id) => ({\n                  action: {\n                    content: \"View\",\n                    onClick: () => {\n                      sonnerToast.dismiss(id)\n                    },\n                  },\n                }),\n              })\n            }}\n          >\n            With Action\n          </Button>\n        </div>\n      </div>\n\n      <div className=\"flex flex-col gap-2\">\n        <h3 className=\"text-body-large-strong\">Secondary Toaster</h3>\n        <div className=\"flex gap-2\">\n          <Button\n            variant=\"secondary\"\n            onClick={() => {\n              notifications({\n                toasterId: \"notifications-secondary\",\n                icon: <LayoutWallpaper />,\n                text: \"This notification appears in the secondary toaster at top-right.\",\n              })\n            }}\n          >\n            Secondary Toaster\n          </Button>\n          <Button\n            variant=\"secondary\"\n            onClick={() => {\n              notifications({\n                toasterId: \"notifications-secondary\",\n                html: \"HTML content in <strong>secondary</strong> toaster\",\n                actions: (id) => ({\n                  dismiss: {\n                    content: \"Dismiss\",\n                    onClick: () => {\n                      sonnerToast.dismiss(id)\n                    },\n                  },\n                }),\n              })\n            }}\n          >\n            With Dismiss\n          </Button>\n        </div>\n      </div>\n\n      <div className=\"flex flex-col gap-2\">\n        <h3 className=\"text-body-large-strong\">Sidebar Toaster</h3>\n        <div className=\"flex gap-2\">\n          <Button\n            variant=\"secondary\"\n            onClick={() => {\n              notifications({\n                toasterId: \"notifications-sidebar\",\n                icon: \"📢\",\n                text: \"Sidebar notification for component-specific messages.\",\n              })\n            }}\n          >\n            Sidebar Toaster\n          </Button>\n          <Button\n            variant=\"secondary\"\n            onClick={() => {\n              notifications({\n                toasterId: \"notifications-sidebar\",\n                icon: <LayoutWallpaper />,\n                text: \"Notification with both action and dismiss buttons\",\n                actions: (id) => ({\n                  action: {\n                    content: \"Action\",\n                    onClick: () => {\n                      sonnerToast.dismiss(id)\n                    },\n                  },\n                  dismiss: {\n                    content: \"Dismiss\",\n                    onClick: () => {\n                      sonnerToast.dismiss(id)\n                    },\n                  },\n                }),\n              })\n            }}\n          >\n            Full Actions\n          </Button>\n        </div>\n      </div>\n\n      <div className=\"text-secondary-foreground text-body-small\">\n        <p className=\"font-strong\">Usage:</p>\n        <p>\n          Multiple Toasters allow you to separate notifications by context or priority. Each\n          Toaster can have its own position, offset, and configuration. Use the{\" \"}\n          <code>toasterId</code> prop to target a specific Toaster when calling{\" \"}\n          <code>notifications()</code>.\n        </p>\n      </div>\n    </div>\n  );\n}"
    },
    {
      "id": "status-notifications--use-effect",
      "name": "Use Effect",
      "exportName": "UseEffect",
      "description": "",
      "source": ""
    }
  ]
}